tests/test_generator.py
tests/test_validator.py
uuid7/__init__.py
uuid7/generator.py
uuid7/validator.py
uuidv7gen-1.0.3.dist-info/licenses/LICENSE
uuidv7gen-1.0.3.dist-info/METADATA
uuidv7gen-1.0.3.dist-info/WHEEL
uuidv7gen-1.0.3.dist-info/top_level.txt
uuidv7gen-1.0.3.dist-info/RECORD
